setup.py
hotelindex/__init__.py
hotelindex/config.py
hotelindex/utility.py
hotelindex.egg-info/PKG-INFO
hotelindex.egg-info/SOURCES.txt
hotelindex.egg-info/dependency_links.txt
hotelindex.egg-info/not-zip-safe
hotelindex.egg-info/top_level.txt
hotelindex/crawler/Wyn88Crawler.py
hotelindex/crawler/__init__.py