Metadata-Version: 1.1
Name: hotelindex
Version: 0.17
Summary: a crawler to get common hotel's room prices
Home-page: https://github.com/hotelindex/hotelindex
Author: zhoumx
Author-email: franky.z.super@hotmail.com
License: UNKNOWN
Keywords: crawler hotel plateno wyn88
Platform: UNKNOWN
Classifier: Programming Language :: Python :: 3.6
